suddendeath/__init__.py
suddendeath/__main__.py
suddendeath-0.5.2.dist-info/LICENSE
suddendeath-0.5.2.dist-info/METADATA
suddendeath-0.5.2.dist-info/WHEEL
suddendeath-0.5.2.dist-info/top_level.txt
suddendeath-0.5.2.dist-info/RECORD
