Metadata-Version: 2.1
Name: suddendeath
Version: 0.5.2
Summary: suddendeath generates 突然の死 message.
Author-email: Yoshi Yamaguchi <ymotongpoo@gmail.com>
License: Apache License
Project-URL: Source Code, https://github.com/ymotongpoo/pysuddendeath
Project-URL: Issue Tracker, https://github.com/ymotongpoo/pysuddendeath/issues
Classifier: Development Status :: 4 - Beta
Classifier: Environment :: Console
Classifier: License :: OSI Approved :: Apache Software License
Classifier: Natural Language :: English
Classifier: Natural Language :: Japanese
Classifier: Programming Language :: Python :: 3 :: Only
Classifier: Programming Language :: Python :: Implementation :: CPython
Classifier: Topic :: Utilities
Requires-Python: >=3.7
License-File: LICENSE
